maskrcnn/__init__.py
maskrcnn-0.0.1.dist-info/LICENSE
maskrcnn-0.0.1.dist-info/METADATA
maskrcnn-0.0.1.dist-info/WHEEL
maskrcnn-0.0.1.dist-info/top_level.txt
maskrcnn-0.0.1.dist-info/RECORD
