Metadata-Version: 2.1
Name: maskrcnn
Version: 0.0.1
Summary: Simple Mask RCNN implementation in Pytorch for educational purposes
Home-page: https://github.com/quanhua92/maskrcnn-pytorch
Author: Quan Hua
Author-email: quanhua92@gmail.com
License: UNKNOWN
Platform: UNKNOWN
Classifier: Programming Language :: Python :: 2.7
Classifier: Programming Language :: Python :: 3
Classifier: License :: OSI Approved :: MIT License
Classifier: Operating System :: OS Independent
